[
    {
        "name": "Crit Rate",
        "stats": "90%"
    },
    {
        "name": "Phys Dmg",
        "stats": "100%"
    },
    {
        "name": "Mag Dmg",
        "stats": "100%"
    },
    {
        "name": "Phys Dmg Dec",
        "stats": "90%"
    },
    {
        "name": "Mag Dmg Dec",
        "stats": "90%"
    },
    {
        "name": "Phys Def",
        "stats": "99%"
    },
    {
        "name": "Mag Deg",
        "stats": "99%"
    },
    {
        "name": "Acc",
        "stats": "99%"
    },
    {
        "name": "Evd",
        "stats": "90%"
    },
    {
        "name": "Block Rate",
        "stats": "90%"
    },
    {
        "name": "Pen Rate",
        "stats": "90%"
    },
    {
        "name": "Exp Inc",
        "stats": "250%"
    },
    {
        "name": "Mesos Acq",
        "stats": "300%"
    },
    {
        "name": "Item Drop",
        "stats": "300%"
    }
]